optjet/__init__.py
optjet/md_encoder.cpython-312-x86_64-linux-gnu.so
optjet/quante.cpython-312-x86_64-linux-gnu.so
optjet-0.2.7.2362.dist-info/licenses/LICENSE.txt
optjet-0.2.7.2362.dist-info/METADATA
optjet-0.2.7.2362.dist-info/WHEEL
optjet-0.2.7.2362.dist-info/top_level.txt
optjet-0.2.7.2362.dist-info/RECORD
