Metadata-Version: 2.4
Name: optjet
Version: 0.2.7.2362
Summary: optjet - package of Solvers and Transformers from 'Quantum Systems'
Author-email: sea <es@qusolve.ru>
License-Expression: LicenseRef-Proprietary
Project-URL: Homepage, https://en.qusolve.ru/
Project-URL: Issues, https://en.qusolve.ru/
Keywords: QuSolve,optjet,quant,SAT solver,LP solver,linear solver,LP,MIP,MILP,SAT,CNF,WCNF,CNF encoder,MaxSAT,pseudo-boolean constraint
Platform: manylinux_2_27_x86_64
Classifier: Programming Language :: Python :: 3
Classifier: Programming Language :: Python :: 3.8
Classifier: Programming Language :: Python :: 3.9
Classifier: Programming Language :: Python :: 3.10
Classifier: Programming Language :: Python :: 3.11
Classifier: Programming Language :: Python :: 3.12
Classifier: Programming Language :: C++
Classifier: Operating System :: Microsoft :: Windows
Classifier: Operating System :: POSIX :: Linux
Classifier: Operating System :: MacOS
Classifier: Topic :: Scientific/Engineering :: Mathematics
Requires-Python: <3.13,>=3.8
License-File: LICENSE.txt
Dynamic: license-file
